clcert_chachagen/__init__.py
clcert_chachagen/chacha20_generator.py
clcert_chachagen-1.1.dist-info/METADATA
clcert_chachagen-1.1.dist-info/WHEEL
clcert_chachagen-1.1.dist-info/top_level.txt
clcert_chachagen-1.1.dist-info/RECORD
