Metadata-Version: 2.1
Name: clcert-chachagen
Version: 1.1
Summary: Library of random related utilities, based on the ChaCha20 stream cipher
Home-page: https://github.com/clcert/ChaCha20-Generator-Utilities/tree/master/python
Author: Camilo Gómez, Franco Pino
Author-email: random@uchile.cl 
License: UNKNOWN
Platform: UNKNOWN
Requires-Dist: pycryptodome (>=3.8.1)
